randlib/__init__.py
randlib/randomlib.py
randlib-0.0.1.dist-info/LICENSE
randlib-0.0.1.dist-info/METADATA
randlib-0.0.1.dist-info/WHEEL
randlib-0.0.1.dist-info/top_level.txt
randlib-0.0.1.dist-info/RECORD
