Metadata-Version: 2.1
Name: randlib
Version: 0.0.1
Summary: A small and lightweight package for generating randomness.
Author-email: Abolfazl Malekpour <abolfazlmalekpour47@gmail.com>
Project-URL: Homepage, https://github.com/Aboly47/randlib/
Project-URL: Issues, https://github.com/Aboly47/randlib/issues
Classifier: Programming Language :: Python :: 3
Classifier: License :: OSI Approved :: MIT License
Classifier: Operating System :: OS Independent
Requires-Python: >=3.7
License-File: LICENSE
